[ 
    {
        "_id":1,
        "Name":"Ranit",
        "Classes":"Phython",
        "Day":"Sun-Mon",
        "slot":"1:00-3:00"
  
},
    {
        "_id":2,
        "Name":"Abdullah",
        "Classes":"Phython",
        "Day":"Sun-Mon",
        "slot":"1:00-3:00"

},
    {
        "_id":3,
        "Classes":"Phython",
        "Name":"hanif",
        "Day":"Sun-Mon",
        "slot":"1:00-3:00"

},
    {
        "_id":4,
        "Classes":"Phython",
        "Name":"Ranit",
        "Day":"Sun-Mon",
        "slot":"1:00-3:00"

},
    {
        "_id":5,
        "Classes":"Phython",
        "Name":"Ranit",
        "Day":"Sun-Mon",
        "slot":"1:00-3:00"

},
    {
        "_id":6,
        "Classes":"Phython",
        "Name":"Ranit",
        "Day":"Sun-Mon",
        "slot":"1:00-3:00"

},
    {
        "_id":7,
        "Classes":"Phython",
        "Name":"Ranit",
        "Day":"Sun-Mon",
        "slot":"1:00-3:00"
},
    {
        "_id":8,
        "Classes":"Phython",
        "Name":"Ranit",
        "Day":"Sun-Mon",
        "slot":"1:00-3:00"
},
{
    "_id":9,
    "Classes":"Phython",
    "Name":"Ranit",
    "Day":"Sun-Mon",
    "slot":"1:00-3:00"

}

]